{"cameraMode":{"drawMode":0,"name":"Shaded","section":"Shading Mode"},"sceneLighting":true,"audioPlay":false,"sceneViewState":{"m_AlwaysRefresh":false,"showFog":true,"showSkybox":true,"showFlares":true,"showImageEffects":true,"showParticleSystems":true,"showVisualEffectGraphs":true,"m_FxEnabled":true},"in2DMode":false,"pivot":{"x":3.7754745483398439,"y":-7.431558132171631,"z":6.71159553527832},"rotation":{"x":-0.3779633343219757,"y":-0.2618181109428406,"z":0.11233705282211304,"w":-0.8808974027633667},"size":8.083311080932618,"orthographic":false}